django_login_history2/__init__.py
django_login_history2/admin.py
django_login_history2/app_settings.py
django_login_history2/apps.py
django_login_history2/dto.py
django_login_history2/helper.py
django_login_history2/logger.py
django_login_history2/models.py
django_login_history2/tests.py
django_login_history2/utils.py
django_login_history2/migrations/0001_initial.py
django_login_history2/migrations/0002_login_logout_at_alter_login_city_and_more.py
django_login_history2/migrations/__init__.py
django_login_history2/mock/__init__.py
django_login_history2/mock/ip_api.py
django_login_history2-0.0.9.dist-info/LICENSE
django_login_history2-0.0.9.dist-info/METADATA
django_login_history2-0.0.9.dist-info/WHEEL
django_login_history2-0.0.9.dist-info/top_level.txt
django_login_history2-0.0.9.dist-info/RECORD
