Metadata-Version: 2.1
Name: django_login_history2
Version: 0.0.9
Summary: It's easy to use, plug-in django app that once included, stores logins history (with device data, like IP, user-agent, location etc.) of all users
Home-page: https://github.com/riquedev/django-login-history2
Author: Henrique da Silva Santos
Author-email: rique_dev@hotmail.com
License: MIT License
Project-URL: Bug Tracker, https://github.com/riquedev/django-login-history2/issues
Project-URL: Repository, https://github.com/riquedev/django-login-history2
Keywords: security,django,login,location,session,ip,authenticate
Classifier: Framework :: Django
Classifier: Intended Audience :: Developers
Classifier: Programming Language :: Python :: 3
Classifier: Programming Language :: Python :: 3.8
Classifier: Programming Language :: Python :: 3.9
Classifier: Programming Language :: Python :: 3.10
Classifier: Programming Language :: Python :: 3.11
Classifier: License :: OSI Approved :: MIT License
Classifier: Operating System :: OS Independent
Requires-Python: >=3.8
License-File: LICENSE
Requires-Dist: Django >=3.2.13
Requires-Dist: django-ipware >=4.0.2
Requires-Dist: requests >=2.31.0
Provides-Extra: dev
Requires-Dist: pytest ; extra == 'dev'
Requires-Dist: tox ; extra == 'dev'
Requires-Dist: black ; extra == 'dev'
